rustlets-0.3.2.dist-info/METADATA
rustlets-0.3.2.dist-info/WHEEL
rustlets/__init__.py
rustlets/rustlets.cpython-310-arm-linux-gnueabihf.so
rustlets-0.3.2.dist-info/RECORD
